pyTooling/Packaging/__init__.py
pyTooling.Packaging-0.5.0.dist-info/LICENSE.md
pyTooling.Packaging-0.5.0.dist-info/METADATA
pyTooling.Packaging-0.5.0.dist-info/WHEEL
pyTooling.Packaging-0.5.0.dist-info/top_level.txt
pyTooling.Packaging-0.5.0.dist-info/RECORD
