Metadata-Version: 2.1
Name: pyTooling.Packaging
Version: 0.5.0
Summary: A set of helper functions to describe a Python package for setuptools.
Home-page: https://GitHub.com/pyTooling/pyTooling.Packaging
Author: Patrick Lehmann
Author-email: Paebbels@gmail.com
License: Apache-2.0
Project-URL: Documentation, https://pyTooling.GitHub.io/pyTooling.Packaging
Project-URL: Source Code, https://GitHub.com/pyTooling/pyTooling.Packaging
Project-URL: Issue Tracker, https://GitHub.com/pyTooling/pyTooling.Packaging/issues
Keywords: setuptools,package,wheel,installation,packaging
Platform: UNKNOWN
Classifier: Operating System :: OS Independent
Classifier: Intended Audience :: Developers
Classifier: Topic :: Utilities
Classifier: License :: OSI Approved :: Apache Software License
Classifier: Programming Language :: Python :: 3 :: Only
Classifier: Programming Language :: Python :: 3.8
Classifier: Programming Language :: Python :: 3.9
Classifier: Programming Language :: Python :: 3.10
Classifier: Development Status :: 4 - Beta
Requires-Python: >=3.8
License-File: LICENSE.md
Requires-Dist: pyTooling (>=1.6.1)
